{
  "schemaVersion": 1,
  "id": "healthmod",
  "version": "${version}",
  "name": "HealthMod",
  "description": "A mod which adds health related items.",
  "authors": [
    "xf8b"
  ],
  "contributors": [
    "Secnyt"
  ],
  "contact": {
    "website": "https://www.curseforge.com/minecraft/mc-mods/healthmod",
    "repo": "https://github.com/xf8b/HealthMod"
  },
  "license": "GPL-3.0",
  "icon": "icon.png",
  "environment": "*",
  "entrypoints": {
    "main": [
      "io.github.xf8b.healthmod.HealthMod"
    ],
    "client": [
      "io.github.xf8b.healthmod.client.HealthModClient"
    ],
    "rrp:pregen": [
      "io.github.xf8b.healthmod.HealthModRRPPregenEntrypoint"
    ]
  },
  "mixins": [
    "healthmod.mixins.json"
  ],
  "depends": {
    "minecraft": "1.16.2",
    "fabric": "*",
    "fabricloader": ">=0.9.3+build.207"
  }
}
